utility_manager/__init__.py
utility_manager/dbdelta_manager.py
databricks_delta_utility-0.1.0.dist-info/License.lic
databricks_delta_utility-0.1.0.dist-info/METADATA
databricks_delta_utility-0.1.0.dist-info/WHEEL
databricks_delta_utility-0.1.0.dist-info/top_level.txt
databricks_delta_utility-0.1.0.dist-info/RECORD
